acquisition_decisions_legacy/__init__.py
acquisition_decisions_legacy/__main__.py
acquisition_decisions_legacy/dissect.py
acquisition_decisions_legacy/meta.py
acquisition_decisions_legacy/utils.py
acquisition_decisions_legacy-0.0.3.dist-info/WHEEL
acquisition_decisions_legacy-0.0.3.dist-info/METADATA
acquisition_decisions_legacy-0.0.3.dist-info/RECORD
