Metadata-Version: 2.1
Name: acquisition-decisions-legacy
Version: 0.0.3
Summary: Processes decisions before 1996. The Philippine Supreme Court's digital library starts in 1996.
Author: Marcelino G. Veloso III
Author-email: mars@veloso.one
Requires-Python: >=3.10,<4.0
Classifier: Programming Language :: Python :: 3
Classifier: Programming Language :: Python :: 3.10
Requires-Dist: acquisition-case-transform (>=0.1.2,<0.2.0)
Requires-Dist: acquisition-ruling-phrase (>=0.3.1,<0.4.0)
Requires-Dist: acquisition-sanitizer (>=0.4.1,<0.5.0)
Requires-Dist: httpx (>=0.22,<0.23)
